peche/__init__.py
peche/manager.py
peche/configuration/__init__.py
peche/configuration/configuration.py
peche/context/__init__.py
peche/context/context.py
peche/contrib/__init__.py
peche/contrib/logging/__init__.py
peche/contrib/logging/handlers/__init__.py
peche/contrib/logging/handlers/kinesis.py
peche/logging/__init__.py
peche/logging/event.py
peche/logging/levels.py
peche/logging/logger.py
peche/logging/logger_totes.py
peche/logging/bridge/__init__.py
peche/logging/bridge/bridge.py
peche/logging/bridge/handler.py
peche/logging/handlers/__init__.py
peche/logging/handlers/handler.py
peche/logging/handlers/stdout.py
peche/logging/handlers/stdout_colour.py
peche/logging/handlers/text_file.py
peche-0.1.0.dist-info/DESCRIPTION.rst
peche-0.1.0.dist-info/METADATA
peche-0.1.0.dist-info/RECORD
peche-0.1.0.dist-info/WHEEL
peche-0.1.0.dist-info/metadata.json
peche-0.1.0.dist-info/pbr.json
peche-0.1.0.dist-info/top_level.txt
