Metadata-Version: 2.0
Name: peche
Version: 0.1.0
Summary: UNKNOWN
Home-page: UNKNOWN
Author: Mihir Singh (@citruspi)
Author-email: hello@mihirsingh.com
License: UNKNOWN
Platform: any
Requires-Dist: termcolor (==1.1.0)
